LICENSE.txt
MANIFEST.in
README.md
pyproject.toml
setup.cfg
src/pycro_hal/__init__.py
src/pycro_hal/build_info.py
src/pycro_hal/cfg.py
src/pycro_hal/constants.py
src/pycro_hal/constants_version.py
src/pycro_hal/pycro_hal_interface.py
src/pycro_hal/svc.py
src/pycro_hal/uart_hal_interface.py
src/pycro_hal.egg-info/PKG-INFO
src/pycro_hal.egg-info/SOURCES.txt
src/pycro_hal.egg-info/dependency_links.txt
src/pycro_hal.egg-info/requires.txt
src/pycro_hal.egg-info/top_level.txt