Metadata-Version: 2.4
Name: pycro-hal
Version: 0.1.1
Summary: python module to drive a microprocessor HAL interface
Author-email: "J. Arrizza" <cppgent0@gmail.com>
Maintainer-email: "J. Arrizza" <cppgent0@gmail.com>
License-Expression: MIT
Project-URL: Website, https://arrizza.com/pycro-hal
Project-URL: Source, https://bitbucket.org/arrizza-public/pycro-hal/src/master
Project-URL: Download, https://bitbucket.org/arrizza-public/pycro-hal/get/master.zip
Keywords: arduino,serial,interface
Classifier: Development Status :: 4 - Beta
Classifier: Environment :: Console
Classifier: Topic :: Utilities
Classifier: Intended Audience :: Developers
Classifier: Programming Language :: Python :: 3.10
Classifier: Programming Language :: Python :: 3.12
Requires-Python: >=3.9
License-File: LICENSE.txt
Requires-Dist: pyserial
Requires-Dist: falcon-logger
Dynamic: license-file
